clgen/__init__.py
clgen/clgen.py
clgen/config.py
clgen-1.0.0.dist-info/METADATA
clgen-1.0.0.dist-info/WHEEL
clgen-1.0.0.dist-info/entry_points.txt
clgen-1.0.0.dist-info/top_level.txt
clgen-1.0.0.dist-info/RECORD
