Metadata-Version: 2.1
Name: clgen
Version: 1.0.0
Summary: OpenAI GPT based cover letter generator.
Home-page: https://github.com/willsamu/clgen
Author: Samuel Will
Author-email: will.samuel@protonmail.com
Keywords: OpenAI,CV,cover letter,ai generator
Classifier: Development Status :: 1 - Planning
Classifier: Intended Audience :: Developers
Classifier: Programming Language :: Python :: 3
Classifier: Operating System :: Unix
Classifier: Operating System :: MacOS :: MacOS X
Requires-Dist: click
Requires-Dist: python-dotenv
Requires-Dist: requests
Requires-Dist: markdown
Requires-Dist: openai
